{
  "period": "2027-Q4",
  "description": "Advanced ckSOL NFT Features: Enhanced marketplace tools, cross-chain collection management, and 4X mobile development, expand platform capabilities, and enhance autonomous systems.",
  "completed": 0,
  "total": 4,
  "milestones": [
    {
      "title": "4X Mobile Vanguard",
      "description": "Core 4X mobile systems and features",
      "completed": 0,
      "total": 3,
      "tasks": [
        {
          "title": "Core Systems Development",
          "description": "Develop core systems for mobile platform.",
          "completed": 0,
          "total": 3,
          "status": "ToDo",
          "subtasks": [
            {
              "title": "Game Engine Adaptation",
              "description": "Adapt game engine for mobile platforms.",
              "completed": false
            },
            {
              "title": "Core Mechanics",
              "description": "Implement core game mechanics for mobile.",
              "completed": false
            },
            {
              "title": "Performance Framework",
              "description": "Establish mobile performance framework.",
              "completed": false
            }
          ]
        },
        {
          "title": "Mobile UI Implementation",
          "description": "Implement mobile-optimized user interface.",
          "completed": 0,
          "total": 3,
          "status": "ToDo",
          "subtasks": [
            {
              "title": "Interface Design",
              "description": "Implement mobile interface designs.",
              "completed": false
            },
            {
              "title": "Control System",
              "description": "Develop mobile control system.",
              "completed": false
            },
            {
              "title": "UI Performance",
              "description": "Optimize UI performance for mobile.",
              "completed": false
            }
          ]
        },
        {
          "title": "Feature Integration",
          "description": "Begin integration of game features.",
          "completed": 0,
          "total": 3,
          "status": "ToDo",
          "subtasks": [
            {
              "title": "Core Features",
              "description": "Integrate core game features.",
              "completed": false
            },
            {
              "title": "Platform Services",
              "description": "Implement platform-specific services.",
              "completed": false
            },
            {
              "title": "Cross-Platform Features",
              "description": "Begin cross-platform feature integration.",
              "completed": false
            }
          ]
        }
      ]
    },
    {
      "title": "NFT Market Intelligence",
      "description": "Comprehensive NFT trading analytics and insights platform",
      "completed": 0,
      "total": 3,
      "tasks": [
        {
          "title": "Performance Optimization",
          "description": "Optimize platform performance.",
          "completed": 0,
          "total": 3,
          "status": "ToDo",
          "subtasks": [
            {
              "title": "System Performance",
              "description": "Enhance overall system performance.",
              "completed": false
            },
            {
              "title": "Resource Usage",
              "description": "Optimize resource utilization.",
              "completed": false
            },
            {
              "title": "Scalability",
              "description": "Improve platform scalability.",
              "completed": false
            }
          ]
        },
        {
          "title": "Integration Features",
          "description": "Enhance platform integration capabilities.",
          "completed": 0,
          "total": 3,
          "status": "ToDo",
          "subtasks": [
            {
              "title": "API Enhancement",
              "description": "Enhance platform APIs.",
              "completed": false
            },
            {
              "title": "Service Integration",
              "description": "Improve service integration.",
              "completed": false
            },
            {
              "title": "Data Exchange",
              "description": "Optimize data exchange systems.",
              "completed": false
            }
          ]
        },
        {
          "title": "Platform Services",
          "description": "Expand platform service offerings.",
          "completed": 0,
          "total": 3,
          "status": "ToDo",
          "subtasks": [
            {
              "title": "New Services",
              "description": "Implement new platform services.",
              "completed": false
            },
            {
              "title": "Service Enhancement",
              "description": "Enhance existing services.",
              "completed": false
            },
            {
              "title": "Service Management",
              "description": "Improve service management capabilities.",
              "completed": false
            }
          ]
        }
      ]
    },
    {
      "title": "Cross-Chain Collection Nexus",
      "description": "Advanced tools for cross-chain NFT collection management",
      "completed": 0,
      "total": 3,
      "tasks": [
        {
          "title": "AI System Enhancement",
          "description": "Advance AI system capabilities.",
          "completed": 0,
          "total": 3,
          "status": "ToDo",
          "subtasks": [
            {
              "title": "Learning Capabilities",
              "description": "Enhance AI learning systems.",
              "completed": false
            },
            {
              "title": "Decision Systems",
              "description": "Improve decision-making capabilities.",
              "completed": false
            },
            {
              "title": "Performance Optimization",
              "description": "Optimize AI system performance.",
              "completed": false
            }
          ]
        },
        {
          "title": "Automation Framework",
          "description": "Enhance automation framework.",
          "completed": 0,
          "total": 3,
          "status": "ToDo",
          "subtasks": [
            {
              "title": "Process Automation",
              "description": "Improve process automation.",
              "completed": false
            },
            {
              "title": "Task Management",
              "description": "Enhance automated task management.",
              "completed": false
            },
            {
              "title": "Resource Allocation",
              "description": "Optimize resource allocation.",
              "completed": false
            }
          ]
        },
        {
          "title": "System Integration",
          "description": "Advance system integration capabilities.",
          "completed": 0,
          "total": 3,
          "status": "ToDo",
          "subtasks": [
            {
              "title": "Service Integration",
              "description": "Enhance service integration.",
              "completed": false
            },
            {
              "title": "Data Flow",
              "description": "Optimize system data flow.",
              "completed": false
            },
            {
              "title": "Monitoring Systems",
              "description": "Improve system monitoring.",
              "completed": false
            }
          ]
        }
      ]
    },
    {
      "title": "Unified Gaming Exchange",
      "description": "Integrated marketplace across all game platforms",
      "completed": 0,
      "total": 3,
      "tasks": [
        {
          "title": "Platform Synchronization",
          "description": "Enhance platform synchronization.",
          "completed": 0,
          "total": 3,
          "status": "ToDo",
          "subtasks": [
            {
              "title": "Data Sync",
              "description": "Improve data synchronization.",
              "completed": false
            },
            {
              "title": "State Management",
              "description": "Enhance state management.",
              "completed": false
            },
            {
              "title": "Conflict Resolution",
              "description": "Implement advanced conflict resolution.",
              "completed": false
            }
          ]
        },
        {
          "title": "User Experience",
          "description": "Enhance cross-platform user experience.",
          "completed": 0,
          "total": 3,
          "status": "ToDo",
          "subtasks": [
            {
              "title": "Interface Consistency",
              "description": "Ensure consistent user interface.",
              "completed": false
            },
            {
              "title": "Feature Parity",
              "description": "Maintain feature parity across platforms.",
              "completed": false
            },
            {
              "title": "Performance Optimization",
              "description": "Optimize cross-platform performance.",
              "completed": false
            }
          ]
        },
        {
          "title": "Integration Framework",
          "description": "Advance integration framework capabilities.",
          "completed": 0,
          "total": 3,
          "status": "ToDo",
          "subtasks": [
            {
              "title": "API Enhancement",
              "description": "Enhance integration APIs.",
              "completed": false
            },
            {
              "title": "Service Framework",
              "description": "Improve service integration framework.",
              "completed": false
            },
            {
              "title": "Monitoring Systems",
              "description": "Enhance integration monitoring.",
              "completed": false
            }
          ]
        }
      ]
    }
  ]
} 