{
  "period": "2028-Q4",
  "description": "New Game Development, AI Systems Update, Automation Framework",
  "completed": 0,
  "total": 4,
  "milestones": [
    {
      "title": "New Game Core Systems",
      "description": "Core systems for new franchise title",
      "completed": 0,
      "total": 3,
      "tasks": [
        {
          "title": "Core Systems",
          "description": "Develop core game systems.",
          "completed": 0,
          "total": 3,
          "status": "ToDo",
          "subtasks": [
            {
              "title": "Gameplay Mechanics",
              "description": "Implement core gameplay mechanics.",
              "completed": false
            },
            {
              "title": "Technical Framework",
              "description": "Establish technical framework.",
              "completed": false
            },
            {
              "title": "Performance Systems",
              "description": "Implement performance systems.",
              "completed": false
            }
          ]
        },
        {
          "title": "Content Creation",
          "description": "Begin content creation pipeline.",
          "completed": 0,
          "total": 3,
          "status": "ToDo",
          "subtasks": [
            {
              "title": "Asset Pipeline",
              "description": "Establish asset creation pipeline.",
              "completed": false
            },
            {
              "title": "World Building",
              "description": "Begin world development.",
              "completed": false
            },
            {
              "title": "Narrative Elements",
              "description": "Create narrative framework.",
              "completed": false
            }
          ]
        },
        {
          "title": "AI Integration",
          "description": "Integrate AI systems.",
          "completed": 0,
          "total": 3,
          "status": "ToDo",
          "subtasks": [
            {
              "title": "AI Framework",
              "description": "Implement AI framework.",
              "completed": false
            },
            {
              "title": "Learning Systems",
              "description": "Deploy learning capabilities.",
              "completed": false
            },
            {
              "title": "Automation Tools",
              "description": "Integrate automation systems.",
              "completed": false
            }
          ]
        }
      ]
    },
    {
      "title": "AI Systems Enhancement",
      "description": "Updated AI capabilities",
      "completed": 0,
      "total": 3,
      "tasks": [
        {
          "title": "Learning Systems",
          "description": "Advance AI learning capabilities.",
          "completed": 0,
          "total": 3,
          "status": "ToDo",
          "subtasks": [
            {
              "title": "Pattern Recognition",
              "description": "Enhance pattern recognition.",
              "completed": false
            },
            {
              "title": "Adaptation Framework",
              "description": "Improve adaptation systems.",
              "completed": false
            },
            {
              "title": "Knowledge Integration",
              "description": "Advance knowledge systems.",
              "completed": false
            }
          ]
        },
        {
          "title": "Decision Systems",
          "description": "Enhance decision-making capabilities.",
          "completed": 0,
          "total": 3,
          "status": "ToDo",
          "subtasks": [
            {
              "title": "Analysis Framework",
              "description": "Improve analysis systems.",
              "completed": false
            },
            {
              "title": "Decision Automation",
              "description": "Advance decision automation.",
              "completed": false
            },
            {
              "title": "Validation Systems",
              "description": "Enhance validation capabilities.",
              "completed": false
            }
          ]
        },
        {
          "title": "System Integration",
          "description": "Advance system integration.",
          "completed": 0,
          "total": 3,
          "status": "ToDo",
          "subtasks": [
            {
              "title": "Service Integration",
              "description": "Enhance service integration.",
              "completed": false
            },
            {
              "title": "Data Flow",
              "description": "Optimize data systems.",
              "completed": false
            },
            {
              "title": "Performance Optimization",
              "description": "Improve system performance.",
              "completed": false
            }
          ]
        }
      ]
    },
    {
      "title": "Automation Systems",
      "description": "Expanded automation framework",
      "completed": 0,
      "total": 3,
      "tasks": [
        {
          "title": "Development Automation",
          "description": "Advance development automation.",
          "completed": 0,
          "total": 3,
          "status": "ToDo",
          "subtasks": [
            {
              "title": "Code Generation",
              "description": "Enhance code generation.",
              "completed": false
            },
            {
              "title": "Testing Systems",
              "description": "Advance testing automation.",
              "completed": false
            },
            {
              "title": "Deployment Pipeline",
              "description": "Improve deployment systems.",
              "completed": false
            }
          ]
        },
        {
          "title": "Governance Automation",
          "description": "Enhance governance automation.",
          "completed": 0,
          "total": 3,
          "status": "ToDo",
          "subtasks": [
            {
              "title": "Decision Framework",
              "description": "Advance decision systems.",
              "completed": false
            },
            {
              "title": "Policy Implementation",
              "description": "Enhance policy automation.",
              "completed": false
            },
            {
              "title": "Oversight Systems",
              "description": "Implement oversight tools.",
              "completed": false
            }
          ]
        },
        {
          "title": "System Preparation",
          "description": "Prepare systems for full automation.",
          "completed": 0,
          "total": 3,
          "status": "ToDo",
          "subtasks": [
            {
              "title": "Infrastructure",
              "description": "Prepare infrastructure systems.",
              "completed": false
            },
            {
              "title": "Integration Framework",
              "description": "Enhance integration systems.",
              "completed": false
            },
            {
              "title": "Monitoring Tools",
              "description": "Advance monitoring capabilities.",
              "completed": false
            }
          ]
        }
      ]
    },
    {
      "title": "System Transition",
      "description": "Full automation preparation",
      "completed": 0,
      "total": 3,
      "tasks": [
        {
          "title": "Strategy Development",
          "description": "Develop transition strategy.",
          "completed": 0,
          "total": 3,
          "status": "ToDo",
          "subtasks": [
            {
              "title": "Timeline Planning",
              "description": "Create transition timeline.",
              "completed": false
            },
            {
              "title": "Resource Allocation",
              "description": "Plan resource requirements.",
              "completed": false
            },
            {
              "title": "Risk Assessment",
              "description": "Assess transition risks.",
              "completed": false
            }
          ]
        },
        {
          "title": "System Assessment",
          "description": "Assess system readiness.",
          "completed": 0,
          "total": 3,
          "status": "ToDo",
          "subtasks": [
            {
              "title": "Capability Analysis",
              "description": "Analyze system capabilities.",
              "completed": false
            },
            {
              "title": "Gap Identification",
              "description": "Identify capability gaps.",
              "completed": false
            },
            {
              "title": "Solution Planning",
              "description": "Plan gap solutions.",
              "completed": false
            }
          ]
        },
        {
          "title": "Community Preparation",
          "description": "Prepare community for transition.",
          "completed": 0,
          "total": 3,
          "status": "ToDo",
          "subtasks": [
            {
              "title": "Communication Plan",
              "description": "Develop communication strategy.",
              "completed": false
            },
            {
              "title": "Training Programs",
              "description": "Create training materials.",
              "completed": false
            },
            {
              "title": "Support Framework",
              "description": "Establish support systems.",
              "completed": false
            }
          ]
        }
      ]
    }
  ]
} 